single_cycle/control_unit.v
module control_unit(
    input clk,
    input zero,
    input [3:0] opcode,
    input [3:0] operand,
  input [7:0] ram_data,ext_data,
    input [7:0] alu_out,

    output reg [7:0] a,
    output reg [7:0] b,
    output reg [7:0] res,
    output reg [7:0] data_in,
    output reg [2:0] sel,
output reg halt,
   output reg jmp_e,
    output reg ram_we,
    output reg [7:0] addr,
    output reg [7:0] load_add
);

// 1. COMBINATIONAL: Instantly decode signals (Use '=' instead of '<=')
always @(*) begin
    // Default values prevent latches
    halt     = 1'b0;
    jmp_e    = 1'b0;
    ram_we   = 1'b0;
    sel      = 3'b111; 
    addr     = 8'd0;
    load_add = 8'd0;
    data_in  = a; // Ready to write A to RAM at any time

    case(opcode)
        4'b0001: sel = 3'b000; // ADD
        4'b0010: sel = 3'b001; // SUB
        4'b0011: sel = 3'b010; // OR
        4'b0100: sel = 3'b011; // AND
        4'b0101: sel = 3'b100; // XOR
        4'b0110: sel = 3'b101; // SHL
        4'b0111: sel = 3'b110; // SHR
        4'b1000: sel = 3'b111; // PASS A
        4'b1001: addr = {4'b0000, operand}; // LOAD
        4'b1010: begin         // STORE
            addr = {4'b0000, operand};
            ram_we = 1'b1;
        end
        4'b1011: begin      // JMP
            jmp_e = 1'b1;
            load_add = {4'b0000, operand};
        end
        4'b1100: begin  // JMPE
            if(zero) begin
                jmp_e = 1'b1;
                load_add = {4'b0000, operand};
            end
        end
        4'b1111: halt = 1'b1;// HALT
    endcase
end

// 2. SEQUENTIAL: Update physical registers on clock edge (Use '<=')
always @(posedge clk) begin
    case(opcode)
      4'b0001, 4'b0010, 4'b0011, 4'b0100, 4'b0101, 4'b0110: begin
            res <= alu_out;
        end

        4'b0000: begin // Register Operations
            case(operand[3:2])
                2'b00: begin // Destination = A
                    case(operand[1:0])
                        2'b01: a <= b;
                        2'b10: a <= res;
                        2'b11: a <= alu_out;
                    endcase
                end
                2'b01: begin // Destination = B
                    case(operand[1:0])
                        2'b00: b <= a;
                        2'b10: b <= res;
                        2'b11: b <= alu_out;
                    endcase
                end
                2'b10: begin // Destination = RES
                    case(operand[1:0])
                        2'b00: res <= a;
                        2'b01: res <= b;
                        2'b11: res <= alu_out;
                    endcase
                end
            endcase
        end
        4'b1001: a <= ram_data; // LOAD into A
      4'b1101:a<=ext_data;
    endcase
end

endmodule

alu.v
module alu(

 input  [7:0] a,b,
   input  [2:0] sel,

     output reg [7:0] alu_out,
 output reg carry,overflow,zero
);

always @(*) begin

    carry    = 1'b0;
    overflow = 1'b0;
    alu_out  = 8'd0;

    case(sel)

        // ADD
        3'b000:
        begin
            {carry, alu_out} = a + b;
            overflow = (a[7]==b[7]) && (alu_out[7]!=a[7]);
        end

        // SUB
        3'b001:
        begin
            {carry, alu_out} = a - b;
            overflow = (a[7]!=b[7]) && (alu_out[7]!=a[7]);
        end

        3'b010:alu_out = a | b;//or
        3'b011:alu_out = a & b;//and
        3'b100:alu_out = a ^ b;//xor
        3'b101:alu_out = a << 1;//shl
        3'b110:alu_out = a >> 1;//shr
        3'b111:alu_out = a;//hold a
        default:alu_out = 8'd0;

    endcase

    zero = (alu_out == 8'd0);

end

endmodule

data_ram.v
module data_ram(
    input clk,
    input we,
    input [7:0] addr,
    input [7:0] data_in,
    output [7:0] data_out
);

reg [7:0] memory [0:255];

always @(posedge clk) begin
    if(we)
        memory[addr] <= data_in;
end

// Changed from always @(*) to continuous assignment
assign data_out = memory[addr];

endmodule

single_cycle/instruction_mem.v
module instruction_mem(

    input [7:0] addr,

    output reg [7:0] instruction

);

reg [7:0] rom [0:255];

initial
begin

    $readmemb("program.mem",rom);

end

always @(*)
begin

    instruction = rom[addr];

end

endmodule

single_cycle/pc.v
module pc(
    input clk,rst,halt,jmp_e,
   input [7:0] load_add,
    output reg [7:0] pc
);

always @(posedge clk) begin
    if(rst)
        pc <= 0;
    else if(halt)
        pc <= pc;
    else if(jmp_e)
        pc <= load_add;
    else
        pc <= pc + 1;
end
endmodule

design.sv
// Code your design here
`include "alu.v"
`include "pc.v"
`include "control_unit.v"
`include "data_ram.v"
`include "instruction_mem.v"


module cpu(

    input clk,
    input rst,
  input [7:0] ext_data

);

    //----------------------------
    // Internal Wires
    //----------------------------

    wire [7:0] pc;

    wire [7:0] instruction;

    wire [3:0] opcode;
    wire [3:0] operand;

    wire [7:0] A;
    wire [7:0] B;
    wire [7:0] RES;

    wire [7:0] alu_out;

    wire [7:0] ram_data;
    wire [7:0] data_in;

    wire [2:0] sel;

    wire carry;
    wire overflow;
    wire zero;

    wire halt;
    wire jmp_e;
    wire ram_we;

    wire [7:0] addr;
    wire [7:0] load_add;

    //----------------------------
    // Instruction Decode
    //----------------------------

    assign opcode  = instruction[7:4];
    assign operand = instruction[3:0];

    //----------------------------
    // Program Counter
    //----------------------------

    pc PC(

        .clk(clk),
        .rst(rst),
        .halt(halt),
        .jmp_e(jmp_e),
        .load_add(load_add),
        .pc(pc)

    );

    //----------------------------
    // Instruction Memory
    //----------------------------

    instruction_mem IM(

        .addr(pc),
        .instruction(instruction)

    );

    //----------------------------
    // Data RAM
    //----------------------------

    data_ram DR(

        .clk(clk),
        .we(ram_we),
        .addr(addr),
        .data_in(data_in),
        .data_out(ram_data)

    );

    //----------------------------
    // ALU
    //----------------------------

    alu ALU(

        .a(A),
        .b(B),
        .sel(sel),

        .alu_out(alu_out),

        .carry(carry),
        .overflow(overflow),
        .zero(zero)

    );

    //----------------------------
    // Control Unit
    //----------------------------

    control_unit CU(

        .clk(clk),

        .zero(zero),

        .opcode(opcode),
        .operand(operand),

        .ram_data(ram_data),
      .ext_data(ext_data),

        .alu_out(alu_out),

        .a(A),
        .b(B),
        .res(RES),

        .data_in(data_in),

        .sel(sel),

        .halt(halt),
        .jmp_e(jmp_e),

        .ram_we(ram_we),

        .addr(addr),

        .load_add(load_add)

    );

endmodule

testbench.sv
module tb;

   reg clk;
    reg rst;
  reg [7:0] ext_data;

    // Instantiate your top module
    cpu dut (
        .clk(clk),
      .rst(rst),
      .ext_data(ext_data)
    );
  
    always #5 clk = ~clk;

    initial begin
        // This generates the waveform file for EPWave
        $dumpfile("dump.vcd");
        $dumpvars(0, tb);

        // Monitor console output for key internal registers
      $monitor("Time=%0t | PC=%b | Inst=%b | Op=%b | A=%d | B=%d | ALU=%d |OV=%d |C=%d | Halt=%b", 
                 $time, dut.pc, dut.instruction, dut.opcode, dut.A, dut.B, dut.alu_out ,dut.overflow ,dut.carry, dut.halt);
      
      ext_data=8'd99;
     clk = 0;
        rst = 1;

        #10 rst = 0; // Release reset

        // PRE-LOAD DATA HERE (AFTER RESET!)
        dut.DR.memory[0] = 8'd10; // Multiplier
        dut.DR.memory[1] = 8'd20; // Multiplicand
        dut.DR.memory[2] = 8'd0;  // Initial Sum = 0
        dut.DR.memory[3] = 8'd1;  // Constant 1

      #1545 $display(dut.DR.memory[2]);
        // Auto-stop simulation after 200 time units to prevent infinite loops
        #2000 $finish;
    end

    always @(posedge clk) begin
        if (dut.halt == 1'b1) begin
            $display("CPU Halted at Time=%0t", $time);
            #10 $finish;
        end
    end

endmodule

single_cycle/dump.vcd
$date
	Tue Aug  4 12:44:14 2026
$end
$version
	Icarus Verilog
$end
$timescale
	1s
$end
$scope module tb $end
$var reg 1 ! clk $end
$var reg 8 " ext_data [7:0] $end
$var reg 1 # rst $end
$scope module dut $end
$var wire 1 ! clk $end
$var wire 8 $ ext_data [7:0] $end
$var wire 1 # rst $end
$var wire 1 % zero $end
$var wire 3 & sel [2:0] $end
$var wire 1 ' ram_we $end
$var wire 8 ( ram_data [7:0] $end
$var wire 8 ) pc [7:0] $end
$var wire 1 * overflow $end
$var wire 4 + operand [3:0] $end
$var wire 4 , opcode [3:0] $end
$var wire 8 - load_add [7:0] $end
$var wire 1 . jmp_e $end
$var wire 8 / instruction [7:0] $end
$var wire 1 0 halt $end
$var wire 8 1 data_in [7:0] $end
$var wire 1 2 carry $end
$var wire 8 3 alu_out [7:0] $end
$var wire 8 4 addr [7:0] $end
$var wire 8 5 RES [7:0] $end
$var wire 8 6 B [7:0] $end
$var wire 8 7 A [7:0] $end
$scope module ALU $end
$var wire 3 8 sel [2:0] $end
$var wire 8 9 b [7:0] $end
$var wire 8 : a [7:0] $end
$var reg 8 ; alu_out [7:0] $end
$var reg 1 2 carry $end
$var reg 1 * overflow $end
$var reg 1 % zero $end
$upscope $end
$scope module CU $end
$var wire 8 < alu_out [7:0] $end
$var wire 1 ! clk $end
$var wire 8 = ext_data [7:0] $end
$var wire 4 > opcode [3:0] $end
$var wire 4 ? operand [3:0] $end
$var wire 1 % zero $end
$var wire 8 @ ram_data [7:0] $end
$var reg 8 A a [7:0] $end
$var reg 8 B addr [7:0] $end
$var reg 8 C b [7:0] $end
$var reg 8 D data_in [7:0] $end
$var reg 1 0 halt $end
$var reg 1 . jmp_e $end
$var reg 8 E load_add [7:0] $end
$var reg 1 ' ram_we $end
$var reg 8 F res [7:0] $end
$var reg 3 G sel [2:0] $end
$upscope $end
$scope module DR $end
$var wire 8 H addr [7:0] $end
$var wire 1 ! clk $end
$var wire 8 I data_in [7:0] $end
$var wire 1 ' we $end
$var reg 8 J data_out [7:0] $end
$upscope $end
$scope module IM $end
$var wire 8 K addr [7:0] $end
$var reg 8 L instruction [7:0] $end
$upscope $end
$scope module PC $end
$var wire 1 ! clk $end
$var wire 1 0 halt $end
$var wire 1 . jmp_e $end
$var wire 8 M load_add [7:0] $end
$var wire 1 # rst $end
$var reg 8 N pc [7:0] $end
$upscope $end
$upscope $end
$upscope $end
$enddefinitions $end
$comment Show the parameter values. $end
$dumpall
$end
#0
$dumpvars
bx N
bx M
bx L
bx K
bx J
bx I
bx H
bx G
bx F
bx E
bx D
bx C
bx B
bx A
bx @
bx ?
bx >
b1100011 =
bx <
bx ;
bx :
bx 9
bx 8
bx 7
bx 6
bx 5
bx 4
bx 3
x2
bx 1
x0
bx /
x.
bx -
bx ,
bx +
x*
bx )
bx (
x'
bx &
x%
b1100011 $
1#
b1100011 "
0!
$end
#5
b1010 (
b1010 @
b1010 J
bx 3
bx ;
bx <
0*
02
b0 -
b0 E
b0 M
b0 4
b0 B
b0 H
b111 &
b111 8
b111 G
0'
0.
00
b0 +
b0 ?
b1101 ,
b1101 >
b11010000 /
b11010000 L
b0 )
b0 K
b0 N
1!
#10
0!
0#
#15
b100 +
b100 ?
b0 ,
b0 >
0%
b1100011 3
b1100011 ;
b1100011 <
b1100011 1
b1100011 D
b1100011 I
b100 /
b100 L
b1100011 7
b1100011 :
b1100011 A
b1 )
b1 K
b1 N
1!
#20
0!
#25
b0 +
b0 ?
b1001 ,
b1001 >
b10010000 /
b10010000 L
b1100011 3
b1100011 ;
b1100011 <
b10 )
b10 K
b10 N
b1100011 6
b1100011 9
b1100011 C
1!
#30
0!
#35
b110 -
b110 E
b110 M
1.
b110 +
b110 ?
b1011 ,
b1011 >
b1010 3
b1010 ;
b1010 <
b1010 1
b1010 D
b1010 I
b10110110 /
b10110110 L
b1010 7
b1010 :
b1010 A
b11 )
b11 K
b11 N
1!
#40
0!
#45
bx (
bx @
bx J
1'
b10 4
b10 B
b10 H
b0 -
b0 E
b0 M
0.
b10 +
b10 ?
b1010 ,
b1010 >
b10100010 /
b10100010 L
b110 )
b110 K
b110 N
1!
#50
0!
#55
b1101101 3
b1101101 ;
b1101101 <
b0 &
b0 8
b0 G
b0 4
b0 B
b0 H
0'
b0 +
b0 ?
b1 ,
b1 >
b1010 (
b1010 @
b1010 J
b10000 /
b10000 L
b111 )
b111 K
b111 N
1!
#60
0!
#65
b1101011 3
b1101011 ;
b1101011 <
b10 &
b10 8
b10 G
b11 ,
b11 >
b110000 /
b110000 L
b1000 )
b1000 K
b1000 N
1!
#70
0!
#75
b10 3
b10 ;
b10 <
b11 &
b11 8
b11 G
b100 ,
b100 >
b1000000 /
b1000000 L
b1001 )
b1001 K
b1001 N
1!
#80
0!
#85
b1101001 3
b1101001 ;
b1101001 <
b100 &
b100 8
b100 G
b101 ,
b101 >
b1010000 /
b1010000 L
b1010 )
b1010 K
b1010 N
1!
#90
0!
#95
b10100 3
b10100 ;
b10100 <
b101 &
b101 8
b101 G
b110 ,
b110 >
b1100000 /
b1100000 L
b1011 )
b1011 K
b1011 N
1!
#100
0!
#105
b101 3
b101 ;
b101 <
b110 &
b110 8
b110 G
b111 ,
b111 >
b1110000 /
b1110000 L
b1100 )
b1100 K
b1100 N
1!
#110
0!
#115
b1010 3
b1010 ;
b1010 <
b111 &
b111 8
b111 G
b1000 ,
b1000 >
b10000000 /
b10000000 L
b1101 )
b1101 K
b1101 N
1!
#120
0!
#125
b10100 (
b10100 @
b10100 J
b1 4
b1 B
b1 H
b1 +
b1 ?
b1001 ,
b1001 >
b10010001 /
b10010001 L
b1110 )
b1110 K
b1110 N
1!
#130
0!
#135
12
b1010 (
b1010 @
b1010 J
b1 &
b1 8
b1 G
b0 +
b0 ?
b10 ,
b10 >
b10110001 3
b10110001 ;
b10110001 <
b10100 1
b10100 D
b10100 I
b0 4
b0 B
b0 H
b100000 /
b100000 L
b10100 7
b10100 :
b10100 A
b1111 )
b1111 K
b1111 N
1!
#140
0!
#145
b10100 3
b10100 ;
b10100 <
02
b111 &
b111 8
b111 G
b100 +
b100 ?
b1100 ,
b1100 >
b11000100 /
b11000100 L
b10000 )
b10000 K
b10000 N
1!
#150
0!
#155
10
b0 +
b0 ?
b1111 ,
b1111 >
b11110000 /
b11110000 L
b10001 )
b10001 K
b10001 N
1!
