pipelined_update/register_file.v
module register_file(
    input clk,
    input rst,
    input [3:0] opcode,
    input [3:0] operand,
    input [7:0] alu_out,
    input [7:0] ram_data,
    input [7:0] ext_data,
    
    output reg [7:0] a,
    output reg [7:0] b,
    output reg [7:0] res
);

always @(posedge clk) begin
    if (rst) begin
        a   <= 8'd0;
        b   <= 8'd0;
        res <= 8'd0;
    end else begin
        case(opcode)
            4'b0000: begin // Register Operations
                case(operand[3:2])
                    2'b00: begin // Dest = A
                        case(operand[1:0])
                            2'b01: a <= b;
                            2'b10: a <= res;
                            2'b11: a <= alu_out;
                        endcase
                    end
                    2'b01: begin // Dest = B
                        case(operand[1:0])
                            2'b00: b <= a;
                            2'b10: b <= res;
                            2'b11: b <= alu_out;
                        endcase
                    end
                    2'b10: begin // Dest = RES
                        case(operand[1:0])
                            2'b00: res <= a;
                            2'b01: res <= b;
                            2'b11: res <= alu_out;
                        endcase
                    end
                endcase
            end
            4'b1001: a <= ram_data; // LOAD into A
            4'b1101: a <= ext_data; // EXT LOAD
        endcase
    end
end

endmodule

pipelined_update/data_ram.v
module data_ram(
    input clk,
    input we,
    input [7:0] addr,
    input [7:0] data_in,
    output [7:0] data_out
);

reg [7:0] memory [0:255];

always @(posedge clk) begin
    if(we)
        memory[addr] <= data_in;
end

assign data_out = memory[addr];

endmodule

pipelined_update/ex_mem_reg.v
module ex_mem_reg(
    input clk,
    input rst,
    
    input [3:0] ex_opcode,
    input [3:0] ex_operand,
    input [7:0] ex_alu_out,
    input [7:0] ex_addr,
    input [7:0] ex_data_in,
    input       ex_ram_we,
    
    output reg [3:0] mem_opcode,
    output reg [3:0] mem_operand,
    output reg [7:0] mem_alu_out,
    output reg [7:0] mem_addr,
    output reg [7:0] mem_data_in,
    output reg       mem_ram_we
);

always @(posedge clk) begin
    if (rst) begin
        mem_opcode  <= 4'd0;
        mem_operand <= 4'd0;
        mem_alu_out <= 8'd0;
        mem_addr    <= 8'd0;
        mem_data_in <= 8'd0;
        mem_ram_we  <= 1'b0;
    end else begin
        mem_opcode  <= ex_opcode;
        mem_operand <= ex_operand;
        mem_alu_out <= ex_alu_out;
        mem_addr    <= ex_addr;
        mem_data_in <= ex_data_in;
        mem_ram_we  <= ex_ram_we;
    end
end

endmodule

pipelined_update/control_unit.v
module control_unit(
    input zero,
    input [3:0] opcode,operand,
    input [7:0] a, // Routed from the Forwarding Unit / Register File

    output reg [7:0] data_in,
    output reg [2:0] sel,
    output reg halt,jmp_e,ram_we,
    output reg [7:0] addr,load_add
);

always @(*) begin
    // Default values prevent latches
    halt     = 1'b0;
    jmp_e    = 1'b0;
    ram_we   = 1'b0;
    sel      = 3'b111; 
    addr     = 8'd0;
    load_add = 8'd0;
    data_in  = a; // Route A to RAM by default

    case(opcode)
        4'b0001: sel = 3'b000; // ADD
        4'b0010: sel = 3'b001; // SUB
        4'b0011: sel = 3'b010; // OR
        4'b0100: sel = 3'b011; // AND
        4'b0101: sel = 3'b100; // XOR
        4'b0110: sel = 3'b101; // SHL
        4'b0111: sel = 3'b110; // SHR
        4'b1000: sel = 3'b111; // PASS A
        4'b1001: addr = {4'b0000, operand}; // LOAD
        4'b1010: begin         // STORE
            addr = {4'b0000, operand};
            ram_we = 1'b1;
        end
        4'b1011: begin      // JMP
            jmp_e = 1'b1;
            load_add = {4'b0000, operand};
        end
        4'b1100: begin  // JMPE
            if(zero) begin
                jmp_e = 1'b1;
                load_add = {4'b0000, operand};
            end
        end
        4'b1111: halt = 1'b1;// HALT
    endcase
end

endmodule

pipelined_update/alu.v
module alu(

 input  [7:0] a,b,
   input  [2:0] sel,

     output reg [7:0] alu_out,
 output reg carry,overflow,zero
);

always @(*) begin

    carry    = 1'b0;
    overflow = 1'b0;
    alu_out  = 8'd0;

    case(sel)

        // ADD
        3'b000:
        begin
            {carry, alu_out} = a + b;
            overflow = (a[7]==b[7]) && (alu_out[7]!=a[7]);
        end

        // SUB
        3'b001:
        begin
            {carry, alu_out} = a - b;
            overflow = (a[7]!=b[7]) && (alu_out[7]!=a[7]);
        end

        3'b010:alu_out = a | b;//or
        3'b011:alu_out = a & b;//and
        3'b100:alu_out = a ^ b;//xor
        3'b101:alu_out = a << 1;//shl
        3'b110:alu_out = a >> 1;//shr
        3'b111:alu_out = a;//hold a
        default:alu_out = 8'd0;

    endcase

    zero = (alu_out == 8'd0);

end

endmodule

pipelined_update/forwarding_unit.v
module forwarding_unit(
    input [7:0] reg_A,
    input [7:0] reg_B,
    input [7:0] reg_RES,
    
    input [3:0] mem_opcode,
    input [3:0] mem_operand,
    input [7:0] mem_alu_out,
    input [7:0] ram_data,
    input [7:0] ext_data,
    
    output reg [7:0] fwd_A,
    output reg [7:0] fwd_B
);

always @(*) begin
    fwd_A = reg_A;
    fwd_B = reg_B;
    
    // Check if Stage 3 is updating 'A'
    if (mem_opcode == 4'b1001) begin 
        fwd_A = ram_data; 
    end else if (mem_opcode == 4'b1101) begin 
        fwd_A = ext_data; 
    end else if (mem_opcode == 4'b0000 && mem_operand[3:2] == 2'b00) begin
        case(mem_operand[1:0])
            2'b01: fwd_A = reg_B;       
            2'b10: fwd_A = reg_RES;     
            2'b11: fwd_A = mem_alu_out; 
        endcase
    end
    
    // Check if Stage 3 is updating 'B'
    if (mem_opcode == 4'b0000 && mem_operand[3:2] == 2'b01) begin
        case(mem_operand[1:0])
            2'b00: fwd_B = reg_A;       
            2'b10: fwd_B = reg_RES;     
            2'b11: fwd_B = mem_alu_out; 
        endcase
    end
end

endmodule

pipelined_update/if_id_reg.v
module if_id_reg(
    input clk,
    input rst,
    input flush, 
    
    input [7:0] if_pc,
    input [7:0] if_instruction,
    
    output reg [7:0] id_pc,
    output reg [7:0] id_instruction
);

always @(posedge clk) begin
    if (rst || flush) begin
        id_pc          <= 8'd0;
        id_instruction <= 8'd0;
    end else begin
        id_pc          <= if_pc;
        id_instruction <= if_instruction;
    end
end

endmodule

pipelined_update/instruction_mem.v
module instruction_mem(
    input [7:0] addr,
    output [7:0] instruction
);

reg [7:0] rom [0:255];

initial begin
    $readmemb("program.mem", rom);
end

// Changed from always @(*) to continuous assignment
assign instruction = rom[addr];

endmodule

pipelined_update/pc.v
module pc(
    input clk,rst,halt,jmp_e,
   input [7:0] load_add,
    output reg [7:0] pc
);

always @(posedge clk) begin
    if(halt)
        pc <= pc;
    else if(rst)
        pc <= 0;
  else if(jmp_e)
        pc <= load_add;
    else
        pc <= pc + 1;
end

endmodule

pipelined_update/design.sv
`include "alu.v"
`include "pc.v"
`include "control_unit.v"
`include "data_ram.v"
`include "instruction_mem.v"
`include "register_file.v"
`include "if_id_reg.v"
`include "ex_mem_reg.v"
`include "forwarding_unit.v"

module cpu(
    input clk,rst,
    input [7:0] ext_data
);

    // Stage 1 Wires (Fetch)
  wire [7:0] if_pc,if_instruction;
    // Stage 2 Wires (Decode/Execute)
  wire [7:0] id_pc,id_instruction;
  wire [3:0] id_opcode,id_operand;

  wire [7:0] A,B,RES,fwd_A,fwd_B,alu_out,data_in;
    wire [2:0] sel;
    wire zero, carry, overflow;
    wire halt, jmp_e, ram_we;
    wire [7:0] addr, load_add;
    wire flush;

  // Stage 3 Wires (Memory/Write-Back)
  wire [3:0] mem_opcode,mem_operand;
  wire [7:0] mem_alu_out,mem_addr,mem_data_in;
    wire  mem_ram_we;
    wire [7:0] ram_data;

    // Flush logic for control hazards
    assign flush = jmp_e;

   
    // STAGE 1: FETCH
    pc PC(.clk(clk), .rst(rst), .halt(halt), .jmp_e(jmp_e), .load_add(load_add), .pc(if_pc));
    instruction_mem IM(.addr(if_pc), .instruction(if_instruction));

    if_id_reg IF_ID(
        .clk(clk), .rst(rst), .flush(flush),
        .if_pc(if_pc), .if_instruction(if_instruction),
        .id_pc(id_pc), .id_instruction(id_instruction)
    );

    // STAGE 2: DECODE & EXECUTE
    assign id_opcode  = id_instruction[7:4];
    assign id_operand = id_instruction[3:0];

    forwarding_unit FU(
        .reg_A(A), .reg_B(B), .reg_RES(RES),
        .mem_opcode(mem_opcode), .mem_operand(mem_operand),
        .mem_alu_out(mem_alu_out), .ram_data(ram_data), .ext_data(ext_data),
        .fwd_A(fwd_A), .fwd_B(fwd_B)
    );

    alu ALU(
        .a(fwd_A),
        .b(fwd_B),
        .sel(sel), .alu_out(alu_out),
        .carry(carry), .overflow(overflow), .zero(zero)
    );

    control_unit CU(
        .zero(zero), .opcode(id_opcode), .operand(id_operand),
        .a(fwd_A), 
        .data_in(data_in), .sel(sel), .halt(halt),
        .jmp_e(jmp_e), .ram_we(ram_we), .addr(addr), .load_add(load_add)
    );

    ex_mem_reg EX_MEM(
        .clk(clk), .rst(rst),
        .ex_opcode(id_opcode), .ex_operand(id_operand),
        .ex_alu_out(alu_out), .ex_addr(addr), .ex_data_in(data_in), .ex_ram_we(ram_we),
        .mem_opcode(mem_opcode), .mem_operand(mem_operand),
        .mem_alu_out(mem_alu_out), .mem_addr(mem_addr), .mem_data_in(mem_data_in), .mem_ram_we(mem_ram_we)
    );

    // STAGE 3: MEMORY & WRITE-BACK
   
    data_ram DR(
        .clk(clk), .we(mem_ram_we), .addr(mem_addr),
        .data_in(mem_data_in), .data_out(ram_data)
    );

    register_file RF(
        .clk(clk), .rst(rst),
        .opcode(mem_opcode), .operand(mem_operand),
        .alu_out(mem_alu_out), .ram_data(ram_data), .ext_data(ext_data),
        .a(A), .b(B), .res(RES)
    );

   
    // TESTBENCH COMPATIBILITY ALIASES
   
    wire [7:0] pc = if_pc;
    wire [7:0] instruction = if_instruction;
    wire [3:0] opcode = id_opcode;

endmodule

pipelined_update/testbench.sv
module tb;

    reg clk;
    reg rst;
    reg [7:0] ext_data;

    // Instantiate your top module
    cpu dut (
        .clk(clk),
        .rst(rst),
        .ext_data(ext_data)
    );
  
    always #5 clk = ~clk;

    initial begin
        // Generate the waveform file for EPWave
        $dumpfile("dump.vcd");
        $dumpvars(0, tb);

        // Monitor console output for key internal registers
        $monitor("Time=%0t | PC=%b | Inst=%b | Op=%b | A=%d | B=%d | ALU=%d |OV=%d |C=%d | Halt=%b", 
                 $time, dut.pc, dut.instruction, dut.opcode, dut.A, dut.B, dut.alu_out, dut.overflow, dut.carry, dut.halt);
      
        ext_data = 8'd99;
        clk = 0;
        rst = 1;

        #10 rst = 0; // Release reset

        // PRE-LOAD DATA HERE
      dut.DR.memory[0] = 8'd7; // Multiplier
        dut.DR.memory[1] = 8'd20; // Multiplicand
        dut.DR.memory[2] = 8'd0;  // Initial Sum = 0
        dut.DR.memory[3] = 8'd1;  // Constant 1

        // Auto-stop simulation as a fallback to prevent infinite loops
        #2000;
        $display("TIMEOUT: CPU never reached HALT state.");
        $finish;
    end

    // Dynamically print the result exactly when the CPU halts
    always @(posedge clk) begin
        if (dut.halt == 1'b1) begin
            $display("========================================");
            $display(" CPU Halted at Time=%0t", $time);
            $display(" MULTIPLICATION RESULT (RAM[2]) = %d", dut.DR.memory[2]);
            $display("========================================");
            #10 $finish;
        end
    end

endmodule

pipelined_update/dump.vcd
$date
	Wed Aug 26 14:11:11 2026
$end
$version
	Icarus Verilog
$end
$timescale
	1s
$end
$scope module tb $end
$var reg 1 ! clk $end
$var reg 8 " ext_data [7:0] $end
$var reg 1 # rst $end
$scope module dut $end
$var wire 1 ! clk $end
$var wire 8 $ ext_data [7:0] $end
$var wire 1 % flush $end
$var wire 8 & instruction [7:0] $end
$var wire 4 ' opcode [3:0] $end
$var wire 8 ( pc [7:0] $end
$var wire 1 # rst $end
$var wire 1 ) zero $end
$var wire 3 * sel [2:0] $end
$var wire 1 + ram_we $end
$var wire 8 , ram_data [7:0] $end
$var wire 1 - overflow $end
$var wire 1 . mem_ram_we $end
$var wire 4 / mem_operand [3:0] $end
$var wire 4 0 mem_opcode [3:0] $end
$var wire 8 1 mem_data_in [7:0] $end
$var wire 8 2 mem_alu_out [7:0] $end
$var wire 8 3 mem_addr [7:0] $end
$var wire 8 4 load_add [7:0] $end
$var wire 1 5 jmp_e $end
$var wire 8 6 if_pc [7:0] $end
$var wire 8 7 if_instruction [7:0] $end
$var wire 8 8 id_pc [7:0] $end
$var wire 4 9 id_operand [3:0] $end
$var wire 4 : id_opcode [3:0] $end
$var wire 8 ; id_instruction [7:0] $end
$var wire 1 < halt $end
$var wire 8 = fwd_B [7:0] $end
$var wire 8 > fwd_A [7:0] $end
$var wire 8 ? data_in [7:0] $end
$var wire 1 @ carry $end
$var wire 8 A alu_out [7:0] $end
$var wire 8 B addr [7:0] $end
$var wire 8 C RES [7:0] $end
$var wire 8 D B [7:0] $end
$var wire 8 E A [7:0] $end
$scope module ALU $end
$var wire 3 F sel [2:0] $end
$var wire 8 G b [7:0] $end
$var wire 8 H a [7:0] $end
$var reg 8 I alu_out [7:0] $end
$var reg 1 @ carry $end
$var reg 1 - overflow $end
$var reg 1 ) zero $end
$upscope $end
$scope module CU $end
$var wire 4 J opcode [3:0] $end
$var wire 4 K operand [3:0] $end
$var wire 1 ) zero $end
$var wire 8 L a [7:0] $end
$var reg 8 M addr [7:0] $end
$var reg 8 N data_in [7:0] $end
$var reg 1 < halt $end
$var reg 1 5 jmp_e $end
$var reg 8 O load_add [7:0] $end
$var reg 1 + ram_we $end
$var reg 3 P sel [2:0] $end
$upscope $end
$scope module DR $end
$var wire 1 ! clk $end
$var wire 8 Q data_out [7:0] $end
$var wire 1 . we $end
$var wire 8 R data_in [7:0] $end
$var wire 8 S addr [7:0] $end
$upscope $end
$scope module EX_MEM $end
$var wire 1 ! clk $end
$var wire 8 T ex_addr [7:0] $end
$var wire 8 U ex_alu_out [7:0] $end
$var wire 8 V ex_data_in [7:0] $end
$var wire 4 W ex_opcode [3:0] $end
$var wire 4 X ex_operand [3:0] $end
$var wire 1 + ex_ram_we $end
$var wire 1 # rst $end
$var reg 8 Y mem_addr [7:0] $end
$var reg 8 Z mem_alu_out [7:0] $end
$var reg 8 [ mem_data_in [7:0] $end
$var reg 4 \ mem_opcode [3:0] $end
$var reg 4 ] mem_operand [3:0] $end
$var reg 1 . mem_ram_we $end
$upscope $end
$scope module FU $end
$var wire 8 ^ ext_data [7:0] $end
$var wire 8 _ mem_alu_out [7:0] $end
$var wire 4 ` mem_opcode [3:0] $end
$var wire 4 a mem_operand [3:0] $end
$var wire 8 b ram_data [7:0] $end
$var wire 8 c reg_RES [7:0] $end
$var wire 8 d reg_B [7:0] $end
$var wire 8 e reg_A [7:0] $end
$var reg 8 f fwd_A [7:0] $end
$var reg 8 g fwd_B [7:0] $end
$upscope $end
$scope module IF_ID $end
$var wire 1 ! clk $end
$var wire 1 % flush $end
$var wire 1 # rst $end
$var wire 8 h if_pc [7:0] $end
$var wire 8 i if_instruction [7:0] $end
$var reg 8 j id_instruction [7:0] $end
$var reg 8 k id_pc [7:0] $end
$upscope $end
$scope module IM $end
$var wire 8 l instruction [7:0] $end
$var wire 8 m addr [7:0] $end
$upscope $end
$scope module PC $end
$var wire 1 ! clk $end
$var wire 1 < halt $end
$var wire 1 5 jmp_e $end
$var wire 8 n load_add [7:0] $end
$var wire 1 # rst $end
$var reg 8 o pc [7:0] $end
$upscope $end
$scope module RF $end
$var wire 8 p alu_out [7:0] $end
$var wire 1 ! clk $end
$var wire 8 q ext_data [7:0] $end
$var wire 4 r opcode [3:0] $end
$var wire 4 s operand [3:0] $end
$var wire 8 t ram_data [7:0] $end
$var wire 1 # rst $end
$var reg 8 u a [7:0] $end
$var reg 8 v b [7:0] $end
$var reg 8 w res [7:0] $end
$upscope $end
$upscope $end
$upscope $end
$enddefinitions $end
$comment Show the parameter values. $end
$dumpall
$end
#0
$dumpvars
bx w
bx v
bx u
bx t
bx s
bx r
b1100011 q
bx p
bx o
bx n
bx m
bx l
bx k
bx j
bx i
bx h
bx g
bx f
bx e
bx d
bx c
bx b
bx a
bx `
bx _
b1100011 ^
bx ]
bx \
bx [
bx Z
bx Y
bx X
bx W
bx V
bx U
bx T
bx S
bx R
bx Q
bx P
bx O
bx N
bx M
bx L
bx K
bx J
bx I
bx H
bx G
bx F
bx E
bx D
bx C
bx B
bx A
x@
bx ?
bx >
bx =
x<
bx ;
bx :
bx 9
bx 8
bx 7
bx 6
x5
bx 4
bx 3
bx 2
bx 1
bx 0
bx /
x.
x-
bx ,
x+
bx *
x)
bx (
bx '
bx &
x%
b1100011 $
1#
b1100011 "
0!
$end
#5
1)
b0 A
b0 I
b0 U
0-
0@
b0 ?
b0 N
b0 V
b0 4
b0 O
b0 n
b0 B
b0 M
b0 T
b111 *
b111 F
b111 P
0+
0%
05
0<
b0 9
b0 K
b0 X
b0 '
b0 :
b0 J
b0 W
b0 =
b0 G
b0 g
b0 >
b0 H
b0 L
b0 f
b10010011 &
b10010011 7
b10010011 i
b10010011 l
b0 (
b0 6
b0 h
b0 m
b0 o
b0 ;
b0 j
b0 8
b0 k
0.
b0 1
b0 R
b0 [
b0 3
b0 S
b0 Y
b0 2
b0 Z
b0 _
b0 p
b0 /
b0 ]
b0 a
b0 s
b0 0
b0 \
b0 `
b0 r
b0 C
b0 c
b0 w
b0 D
b0 d
b0 v
b0 E
b0 e
b0 u
1!
#10
0!
b1010 ,
b1010 Q
b1010 b
b1010 t
0#
#15
b11 B
b11 M
b11 T
b11 9
b11 K
b11 X
b1001 '
b1001 :
b1001 J
b1001 W
b10010011 ;
b10010011 j
b100 &
b100 7
b100 i
b100 l
b1 (
b1 6
b1 h
b1 m
b1 o
1!
#20
0!
#25
0)
b1 A
b1 I
b1 U
b1 ?
b1 N
b1 V
b0 B
b0 M
b0 T
b100 9
b100 K
b100 X
b0 '
b0 :
b0 J
b0 W
b1 >
b1 H
b1 L
b1 f
b10010000 &
b10010000 7
b10010000 i
b10010000 l
b10 (
b10 6
b10 h
b10 m
b10 o
b100 ;
b100 j
b1 8
b1 k
b1 ,
b1 Q
b1 b
b1 t
b11 3
b11 S
b11 Y
b11 /
b11 ]
b11 a
b11 s
b1001 0
b1001 \
b1001 `
b1001 r
1!
#30
0!
#35
b1 A
b1 I
b1 U
b1 =
b1 G
b1 g
b0 9
b0 K
b0 X
b1001 '
b1001 :
b1001 J
b1001 W
b1 E
b1 e
b1 u
b1 1
b1 R
b1 [
b1010 ,
b1010 Q
b1010 b
b1010 t
b0 3
b0 S
b0 Y
b1 2
b1 Z
b1 _
b1 p
b100 /
b100 ]
b100 a
b100 s
b0 0
b0 \
b0 `
b0 r
b10010000 ;
b10010000 j
b10 8
b10 k
b10000000 &
b10000000 7
b10000000 i
b10000000 l
b11 (
b11 6
b11 h
b11 m
b11 o
1!
#40
0!
#45
b1010 A
b1010 I
b1010 U
b1010 ?
b1010 N
b1010 V
b1000 '
b1000 :
b1000 J
b1000 W
b1010 >
b1010 H
b1010 L
b1010 f
b11001111 &
b11001111 7
b11001111 i
b11001111 l
b100 (
b100 6
b100 h
b100 m
b100 o
b10000000 ;
b10000000 j
b11 8
b11 k
b0 /
b0 ]
b0 a
b0 s
b1001 0
b1001 \
b1001 `
b1001 r
b1 D
b1 d
b1 v
1!
#50
0!
#55
b1111 9
b1111 K
b1111 X
b1100 '
b1100 :
b1100 J
b1100 W
b1010 E
b1010 e
b1010 u
b1010 1
b1010 R
b1010 [
b1010 2
b1010 Z
b1010 _
b1010 p
b1000 0
b1000 \
b1000 `
b1000 r
b11001111 ;
b11001111 j
b100 8
b100 k
b100000 &
b100000 7
b100000 i
b100000 l
b101 (
b101 6
b101 h
b101 m
b101 o
1!
#60
0!
#65
b1001 A
b1001 I
b1001 U
b1 *
b1 F
b1 P
b0 9
b0 K
b0 X
b10 '
b10 :
b10 J
b10 W
b10 &
b10 7
b10 i
b10 l
b110 (
b110 6
b110 h
b110 m
b110 o
b100000 ;
b100000 j
b101 8
b101 k
b1111 /
b1111 ]
b1111 a
b1111 s
b1100 0
b1100 \
b1100 `
b1100 r
1!
#70
0!
#75
b1010 A
b1010 I
b1010 U
b111 *
b111 F
b111 P
b10 9
b10 K
b10 X
b0 '
b0 :
b0 J
b0 W
b1001 2
b1001 Z
b1001 _
b1001 p
b0 /
b0 ]
b0 a
b0 s
b10 0
b10 \
b10 `
b10 r
b10 ;
b10 j
b110 8
b110 k
b10100000 &
b10100000 7
b10100000 i
b10100000 l
b111 (
b111 6
b111 h
b111 m
b111 o
1!
#80
0!
#85
1)
b0 A
b0 I
b0 U
1+
b0 ?
b0 N
b0 V
b0 9
b0 K
b0 X
b1010 '
b1010 :
b1010 J
b1010 W
b0 >
b0 H
b0 L
b0 f
b10010001 &
b10010001 7
b10010001 i
b10010001 l
b1000 (
b1000 6
b1000 h
b1000 m
b1000 o
b10100000 ;
b10100000 j
b111 8
b111 k
b1010 2
b1010 Z
b1010 _
b1010 p
b10 /
b10 ]
b10 a
b10 s
b0 0
b0 \
b0 `
b0 r
1!
#90
0!
#95
b1 B
b1 M
b1 T
0+
b1 9
b1 K
b1 X
b1001 '
b1001 :
b1001 J
b1001 W
b0 E
b0 e
b0 u
1.
b0 1
b0 R
b0 [
b0 2
b0 Z
b0 _
b0 p
b0 /
b0 ]
b0 a
b0 s
b1010 0
b1010 \
b1010 `
b1010 r
b10010001 ;
b10010001 j
b1000 8
b1000 k
b100 &
b100 7
b100 i
b100 l
b1001 (
b1001 6
b1001 h
b1001 m
b1001 o
1!
#100
0!
#105
0)
b10100 A
b10100 I
b10100 U
b10100 ?
b10100 N
b10100 V
b0 B
b0 M
b0 T
b100 9
b100 K
b100 X
b0 '
b0 :
b0 J
b0 W
b10100 >
b10100 H
b10100 L
b10100 f
b10010010 &
b10010010 7
b10010010 i
b10010010 l
b1010 (
b1010 6
b1010 h
b1010 m
b1010 o
b100 ;
b100 j
b1001 8
b1001 k
0.
b1 3
b1 S
b1 Y
b1 /
b1 ]
b1 a
b1 s
b1001 0
b1001 \
b1001 `
b1001 r
b10100 ,
b10100 Q
b10100 b
b10100 t
1!
#110
0!
#115
b10100 A
b10100 I
b10100 U
b10 B
b10 M
b10 T
b10100 =
b10100 G
b10100 g
b10 9
b10 K
b10 X
b1001 '
b1001 :
b1001 J
b1001 W
b10100 E
b10100 e
b10100 u
b10100 1
b10100 R
b10100 [
b0 ,
b0 Q
b0 b
b0 t
b0 3
b0 S
b0 Y
b10100 2
b10100 Z
b10100 _
b10100 p
b100 /
b100 ]
b100 a
b100 s
b0 0
b0 \
b0 `
b0 r
b10010010 ;
b10010010 j
b1010 8
b1010 k
b10000 &
b10000 7
b10000 i
b10000 l
b1011 (
b1011 6
b1011 h
b1011 m
b1011 o
1!
#120
0!
#125
b10100 A
b10100 I
b10100 U
b0 *
b0 F
b0 P
b0 ?
b0 N
b0 V
b0 B
b0 M
b0 T
b0 9
b0 K
b0 X
b1 '
b1 :
b1 J
b1 W
b0 >
b0 H
b0 L
b0 f
b10 &
b10 7
b10 i
b10 l
b1100 (
b1100 6
b1100 h
b1100 m
b1100 o
b10000 ;
b10000 j
b1011 8
b1011 k
b10 3
b10 S
b10 Y
b10 /
b10 ]
b10 a
b10 s
b1001 0
b1001 \
b1001 `
b1001 r
b10100 D
b10100 d
b10100 v
1!
#130
0!
#135
1)
b0 A
b0 I
b0 U
b111 *
b111 F
b111 P
b10 9
b10 K
b10 X
b0 '
b0 :
b0 J
b0 W
b0 E
b0 e
b0 u
b0 1
b0 R
b0 [
b0 3
b0 S
b0 Y
b0 /
b0 ]
b0 a
b0 s
b1 0
b1 \
b1 `
b1 r
b10 ;
b10 j
b1100 8
b1100 k
b10100010 &
b10100010 7
b10100010 i
b10100010 l
b1101 (
b1101 6
b1101 h
b1101 m
b1101 o
1!
#140
0!
#145
1+
b10 B
b10 M
b10 T
b1010 '
b1010 :
b1010 J
b1010 W
b10110000 &
b10110000 7
b10110000 i
b10110000 l
b1110 (
b1110 6
b1110 h
b1110 m
b1110 o
b10100010 ;
b10100010 j
b1101 8
b1101 k
b0 2
b0 Z
b0 _
b0 p
b10 /
b10 ]
b10 a
b10 s
b0 0
b0 \
b0 `
b0 r
1!
#150
0!
#155
1%
15
b0 B
b0 M
b0 T
0+
b0 9
b0 K
b0 X
b1011 '
b1011 :
b1011 J
b1011 W
1.
b10 3
b10 S
b10 Y
b1010 0
b1010 \
b1010 `
b1010 r
b10110000 ;
b10110000 j
b1110 8
b1110 k
b11110000 &
b11110000 7
b11110000 i
b11110000 l
b1111 (
b1111 6
b1111 h
b1111 m
b1111 o
1!
#160
0!
#165
0%
05
b0 '
b0 :
b0 J
b0 W
b10010011 &
b10010011 7
b10010011 i
b10010011 l
b0 (
b0 6
b0 h
b0 m
b0 o
b0 ;
b0 j
b0 8
b0 k
0.
b0 3
b0 S
b0 Y
b0 /
b0 ]
b0 a
b0 s
b1011 0
b1011 \
b1011 `
b1011 r
1!
#170
0!
#175
b11 B
b11 M
b11 T
b11 9
b11 K
b11 X
b1001 '
b1001 :
b1001 J
b1001 W
b0 0
b0 \
b0 `
b0 r
b10010011 ;
b10010011 j
b100 &
b100 7
b100 i
b100 l
b1 (
b1 6
b1 h
b1 m
b1 o
1!
#180
0!
#185
0)
b1 A
b1 I
b1 U
b1 ?
b1 N
b1 V
b0 B
b0 M
b0 T
b100 9
b100 K
b100 X
b0 '
b0 :
b0 J
b0 W
b1 >
b1 H
b1 L
b1 f
b10010000 &
b10010000 7
b10010000 i
b10010000 l
b10 (
b10 6
b10 h
b10 m
b10 o
b100 ;
b100 j
b1 8
b1 k
b1 ,
b1 Q
b1 b
b1 t
b11 3
b11 S
b11 Y
b11 /
b11 ]
b11 a
b11 s
b1001 0
b1001 \
b1001 `
b1001 r
1!
#190
0!
#195
b1 A
b1 I
b1 U
b1 =
b1 G
b1 g
b0 9
b0 K
b0 X
b1001 '
b1001 :
b1001 J
b1001 W
b1 E
b1 e
b1 u
b1 1
b1 R
b1 [
b0 ,
b0 Q
b0 b
b0 t
b0 3
b0 S
b0 Y
b1 2
b1 Z
b1 _
b1 p
b100 /
b100 ]
b100 a
b100 s
b0 0
b0 \
b0 `
b0 r
b10010000 ;
b10010000 j
b10 8
b10 k
b10000000 &
b10000000 7
b10000000 i
b10000000 l
b11 (
b11 6
b11 h
b11 m
b11 o
1!
#200
0!
#205
1)
b0 A
b0 I
b0 U
b0 ?
b0 N
b0 V
b1000 '
b1000 :
b1000 J
b1000 W
b0 >
b0 H
b0 L
b0 f
b11001111 &
b11001111 7
b11001111 i
b11001111 l
b100 (
b100 6
b100 h
b100 m
b100 o
b10000000 ;
b10000000 j
b11 8
b11 k
b0 /
b0 ]
b0 a
b0 s
b1001 0
b1001 \
b1001 `
b1001 r
b1 D
b1 d
b1 v
1!
#210
0!
#215
b1111 4
b1111 O
b1111 n
1%
15
b1111 9
b1111 K
b1111 X
b1100 '
b1100 :
b1100 J
b1100 W
b0 E
b0 e
b0 u
b0 1
b0 R
b0 [
b0 2
b0 Z
b0 _
b0 p
b1000 0
b1000 \
b1000 `
b1000 r
b11001111 ;
b11001111 j
b100 8
b100 k
b100000 &
b100000 7
b100000 i
b100000 l
b101 (
b101 6
b101 h
b101 m
b101 o
1!
#220
0!
#225
b0 4
b0 O
b0 n
0%
05
b0 9
b0 K
b0 X
b0 '
b0 :
b0 J
b0 W
b11110000 &
b11110000 7
b11110000 i
b11110000 l
b1111 (
b1111 6
b1111 h
b1111 m
b1111 o
b0 ;
b0 j
b0 8
b0 k
b1111 /
b1111 ]
b1111 a
b1111 s
b1100 0
b1100 \
b1100 `
b1100 r
1!
#230
0!
#235
1<
b1111 '
b1111 :
b1111 J
b1111 W
b0 /
b0 ]
b0 a
b0 s
b0 0
b0 \
b0 `
b0 r
b11110000 ;
b11110000 j
b1111 8
b1111 k
bx &
bx 7
bx i
bx l
b10000 (
b10000 6
b10000 h
b10000 m
b10000 o
1!
#240
0!
#245
0<
bx 9
bx K
bx X
bx '
bx :
bx J
bx W
bx ;
bx j
b10000 8
b10000 k
b1111 0
b1111 \
b1111 `
b1111 r
1!
#250
0!
#255
bx /
bx ]
bx a
bx s
bx 0
bx \
bx `
bx r
b10001 (
b10001 6
b10001 h
b10001 m
b10001 o
1!
